ptm/__init__.py
ptm/cli.py
ptm/version.py
ptm/syntax/__init__.py
ptm/syntax/arglist.py
ptm/syntax/environ.py
ptm/syntax/include.py
ptm/syntax/loader.py
ptm/syntax/param.py
ptm/syntax/shell.py
ptm/system/__init__.py
ptm/system/builder.py
ptm/system/logger.py
ptm/system/project.py
ptm/system/recipe.py
ptm/system/scheduler.py
ptm/system/watcher.py
phantom_make-0.1.20.dist-info/METADATA
phantom_make-0.1.20.dist-info/WHEEL
phantom_make-0.1.20.dist-info/entry_points.txt
phantom_make-0.1.20.dist-info/top_level.txt
phantom_make-0.1.20.dist-info/RECORD
