Metadata-Version: 2.4
Name: phantom-make
Version: 0.1.20
Summary: A python-based traceable make system
Home-page: https://github.com/Phantom1003/ptm
Author: Phantom1003
Author-email: phantom@zju.edu.cn
Classifier: Programming Language :: Python :: 3
Classifier: License :: OSI Approved :: MIT License
Classifier: Operating System :: OS Independent
Requires-Python: >=3.10
Dynamic: author
Dynamic: author-email
Dynamic: classifier
Dynamic: description
Dynamic: description-content-type
Dynamic: home-page
Dynamic: requires-python
Dynamic: summary
